osrs/__init__.py
osrs/exceptions.py
osrs/asyncio/__init__.py
osrs/asyncio/osrs/__init__.py
osrs/asyncio/osrs/hiscores.py
osrs/asyncio/osrs/itemdb.py
osrs/asyncio/wiki/__init__.py
osrs/asyncio/wiki/prices.py
osrs/sync/__init__.py
osrs/sync/osrs/__init__.py
osrs/sync/runelite/__init__.py
osrs/utils/__init__.py
osrs/utils/ratelimiter.py
osrs-0.0.15.dist-info/licenses/LICENSE
osrs-0.0.15.dist-info/METADATA
osrs-0.0.15.dist-info/WHEEL
osrs-0.0.15.dist-info/top_level.txt
osrs-0.0.15.dist-info/RECORD
