Metadata-Version: 2.4
Name: osrs
Version: 0.0.15
Summary: a wrapper around osrs api's
Author: extreme4all
Project-URL: Homepage, https://github.com/Bot-detector/osrs
Project-URL: Bug Tracker, https://github.com/Bot-detector/osrs/issues
Classifier: Programming Language :: Python :: 3
Classifier: License :: OSI Approved :: MIT License
Classifier: Operating System :: OS Independent
Requires-Python: >=3.10
License-File: LICENSE
Requires-Dist: aiohttp>=3.10.10
Requires-Dist: pydantic>=2.9.2
Requires-Dist: requests>=2.32.3
Dynamic: license-file
